[
  {
    "id": 1,
    "bookingId": "BK1753810055153107",
    "trekId": 1,
    "userEmail": "saugatchaudhary@gmail.com",
    "guideEmail": "sarun-maharjan@guide.com",
    "trekStartDateStr": "2026-07-01"
  },
  {
    "id": 2,
    "bookingId": "BK1753810058211571",
    "trekId": 2,
    "userEmail": "saugatchaudhary@gmail.com",
    "guideEmail": "sarun-maharjan@guide.com",
    "trekStartDateStr": "2026-07-02"
  },
  {
    "id": 3,
    "bookingId": "BK1753810061020412",
    "trekId": 3,
    "userEmail": "saugatchaudhary@gmail.com",
    "guideEmail": "sarun-maharjan@guide.com",
    "trekStartDateStr": "2026-07-03"
  },
  {
    "id": 4,
    "bookingId": "BK1753810063366163",
    "trekId": 4,
    "userEmail": "saugatchaudhary@gmail.com",
    "guideEmail": "sarun-maharjan@guide.com",
    "trekStartDateStr": "2026-07-05"
  },
  {
    "id": 5,
    "bookingId": "BK1753810085843371",
    "trekId": 1,
    "userEmail": "bishesmaharjan@gmail.com",
    "guideEmail": "sarun-maharjan@guide.com",
    "trekStartDateStr": "2026-07-01"
  },
  {
    "id": 6,
    "bookingId": "BK1753810089479854",
    "trekId": 3,
    "userEmail": "bishesmaharjan@gmail.com",
    "guideEmail": "sarun-maharjan@guide.com",
    "trekStartDateStr": "2026-07-03"
  },
  {
    "id": 7,
    "bookingId": "BK1753810109745771",
    "trekId": 4,
    "userEmail": "pramodjungkhatri@gmail.com",
    "guideEmail": "sarun-maharjan@guide.com",
    "trekStartDateStr": "2026-07-05"
  },
  {
    "id": 8,
    "bookingId": "BK1753810113424901",
    "trekId": 3,
    "userEmail": "pramodjungkhatri@gmail.com",
    "guideEmail": "sarun-maharjan@guide.com",
    "trekStartDateStr": "2026-07-03"
  },
  {
    "id": 9,
    "bookingId": "BK1753810145151409",
    "trekId": 2,
    "userEmail": "runamaphu@gmail.com",
    "guideEmail": "sarun-maharjan@guide.com",
    "trekStartDateStr": "2026-07-02"
  },
  {
    "id": 10,
    "bookingId": "BK1753810164061337",
    "trekId": 2,
    "userEmail": "ishleensinghvirdi@gmail.com",
    "guideEmail": "sarun-maharjan@guide.com",
    "trekStartDateStr": "2026-07-02"
  },
  {
    "id": 11,
    "bookingId": "BK1753810168153269",
    "trekId": 4,
    "userEmail": "ishleensinghvirdi@gmail.com",
    "guideEmail": "sarun-maharjan@guide.com",
    "trekStartDateStr": "2026-07-05"
  },
  {
    "id": 12,
    "bookingId": "BK1753810191240237",
    "trekId": 1,
    "userEmail": "prabhashkhadka@gmail.com",
    "guideEmail": "sarun-maharjan@guide.com",
    "trekStartDateStr": "2026-07-01"
  },
  {
    "id": 13,
    "bookingId": "BK1753810194680450",
    "trekId": 4,
    "userEmail": "prabhashkhadka@gmail.com",
    "guideEmail": "sarun-maharjan@guide.com",
    "trekStartDateStr": "2026-07-05"
  },
  {
    "id": 14,
    "bookingId": "BK1753810213964137",
    "trekId": 3,
    "userEmail": "johnshrestha@gmail.com",
    "guideEmail": "sarun-maharjan@guide.com",
    "trekStartDateStr": "2026-07-03"
  },
  {
    "id": 15,
    "bookingId": "BK1753810216913374",
    "trekId": 4,
    "userEmail": "johnshrestha@gmail.com",
    "guideEmail": "sarun-maharjan@guide.com",
    "trekStartDateStr": "2026-07-05"
  },
  {
    "id": 16,
    "bookingId": "BK1753810241745800",
    "trekId": 2,
    "userEmail": "angelshakya@gmail.com",
    "guideEmail": "sarun-maharjan@guide.com",
    "trekStartDateStr": "2026-07-02"
  },
  {
    "id": 17,
    "bookingId": "BK1753812894657944",
    "trekId": 1,
    "userEmail": "saugatchaudhary@gmail.com",
    "guideEmail": "sarun-maharjan@guide.com",
    "trekStartDateStr": "2026-07-01"
  },
  {
    "id": 18,
    "bookingId": "BK1753845436108108",
    "trekId": 3,
    "userEmail": "saugatchaudhary@gmail.com",
    "guideEmail": "sarun-maharjan@guide.com",
    "trekStartDateStr": "2026-07-03"
  },
  {
    "id": 19,
    "bookingId": "BK1753846001800637",
    "trekId": 1,
    "userEmail": "SarunMaharjan@gmail.com",
    "guideEmail": "sarun-maharjan@guide.com",
    "trekStartDateStr": "2026-07-01"
  },
  {
    "id": 20,
    "bookingId": "BK1753846017325450",
    "trekId": 1,
    "userEmail": "SarunMaharjan@gmail.com",
    "guideEmail": "sarun-maharjan@guide.com",
    "trekStartDateStr": "2026-07-01"
  },
  {
    "id": 21,
    "bookingId": "BK1753846303382443",
    "trekId": 5,
    "userEmail": "SarunMaharjan@gmail.com",
    "guideEmail": "rija-bhomi@guide.com",
    "trekStartDateStr": "2025-09-01"
  }
]